README.md
setup.cfg
setup.py
TOPSIS_Pranshu_101853037/__init__.py
TOPSIS_Pranshu_101853037/topsis.py
TOPSIS_Pranshu_101853037.egg-info/PKG-INFO
TOPSIS_Pranshu_101853037.egg-info/SOURCES.txt
TOPSIS_Pranshu_101853037.egg-info/dependency_links.txt
TOPSIS_Pranshu_101853037.egg-info/requires.txt
TOPSIS_Pranshu_101853037.egg-info/top_level.txt