Metadata-Version: 2.1
Name: TOPSIS-Pranshu-101853037
Version: 0.0.1
Summary: This is a Python Package implementing TOPSIS used for multi-criteria decision analysis method
Home-page: https://github.com/pranshu1229/topsispy
Author: Pranshu Jindal
Author-email: pranshujindal7@gmail.com
License: MIT
Download-URL: https://github.com/pranshu1229/topsispy/archive/v_01.tar.gz
Keywords: topsis,becoe,UCS538,TIET
Platform: UNKNOWN
Classifier: Development Status :: 3 - Alpha
Classifier: Intended Audience :: Developers
Classifier: Topic :: Software Development :: Build Tools
Classifier: License :: OSI Approved :: MIT License
